bottle_pypugjs.py
bottle_pypugjs_version.py
bottle_pypugjs-0.1.1.post6.dist-info/LICENSE
bottle_pypugjs-0.1.1.post6.dist-info/METADATA
bottle_pypugjs-0.1.1.post6.dist-info/WHEEL
bottle_pypugjs-0.1.1.post6.dist-info/top_level.txt
bottle_pypugjs-0.1.1.post6.dist-info/RECORD
