Metadata-Version: 2.1
Name: bottle-pypugjs
Version: 0.1.1.post6
Summary: Este es un plugin de bottle para poder usar la libreria de pypugjs en las vistas
Home-page: UNKNOWN
Author: Lorenzo A. Garcia Calzadilla
Author-email: lorenzogarciacalzadilla@gmail.com
Maintainer: 
Maintainer-email: 
License: MIT
Platform: UNKNOWN
Requires-Dist: bottle
Requires-Dist: pypugjs (>=5.8.1)
